setup.py
counterparty_cli.egg-info/PKG-INFO
counterparty_cli.egg-info/SOURCES.txt
counterparty_cli.egg-info/dependency_links.txt
counterparty_cli.egg-info/entry_points.txt
counterparty_cli.egg-info/not-zip-safe
counterparty_cli.egg-info/requires.txt
counterparty_cli.egg-info/top_level.txt
counterpartycli/__init__.py
counterpartycli/client.py
counterpartycli/clientapi.py
counterpartycli/console.py
counterpartycli/messages.py
counterpartycli/server.py
counterpartycli/setup.py
counterpartycli/util.py
counterpartycli/wallet/__init__.py
counterpartycli/wallet/bitcoincore.py
counterpartycli/wallet/btcwallet.py