Metadata-Version: 1.1
Name: counterparty-cli
Version: 1.1.0
Summary: Counterparty Protocol Command-Line Interface
Home-page: http://counterparty.io
Author: Adam Krellenstein
Author-email: adamk@counterparty.io
License: MIT
Download-URL: https://github.com/CounterpartyXCP/counterparty-cli/releases/tag/v1.1.0
Keywords: counterparty,bitcoin
Platform: UNKNOWN
Classifier: Development Status :: 5 - Production/Stable
Classifier: Environment :: Console
Classifier: Intended Audience :: Developers
Classifier: Intended Audience :: End Users/Desktop
Classifier: Intended Audience :: Financial and Insurance Industry
Classifier: License :: OSI Approved :: MIT License
Classifier: Natural Language :: English
Classifier: Operating System :: Microsoft :: Windows
Classifier: Operating System :: POSIX
Classifier: Programming Language :: Python :: 3 :: Only
Classifier: Topic :: Office/Business :: Financial
Classifier: Topic :: System :: Distributed Computing
Provides: counterpartycli
